README.txt
keepassc.py
setup.py
python/keepass/__init__.py
python/keepass/cli.py
python/keepass/header.py
python/keepass/hier.py
python/keepass/infoblock.py
python/keepass/kpdb.py
python/keepass/test_crud.py
python/keepass.egg-info/PKG-INFO
python/keepass.egg-info/SOURCES.txt
python/keepass.egg-info/dependency_links.txt
python/keepass.egg-info/requires.txt
python/keepass.egg-info/top_level.txt