Metadata-Version: 1.1
Name: keepass
Version: 1.1
Summary: Python (both 2 and 3) interface and cli to KeePass file format v3 (used in KeePass V1.x and KeePassX)
Home-page: https://github.com/Friz-zy/python-keepass
Author: ['Brett Viren', 'Jeremy Ehrhardt', 'Filipp Frizzy']
Author-email: filipp.s.frizzy@gmail.com
License: GPLv2+
Keywords: python keepass kdb
Platform: UNKNOWN
Classifier: License :: OSI Approved :: GNU General Public License v2 or later (GPLv2+)
Classifier: Operating System :: OS Independent
Classifier: Programming Language :: Python
Classifier: Programming Language :: Python :: 2
Classifier: Programming Language :: Python :: 3
